global_kmeans_pp/__init__.py
global_kmeans_pp/global_clustering.py
global_kmeans_pp-0.1.0.dist-info/LICENSE
global_kmeans_pp-0.1.0.dist-info/METADATA
global_kmeans_pp-0.1.0.dist-info/WHEEL
global_kmeans_pp-0.1.0.dist-info/top_level.txt
global_kmeans_pp-0.1.0.dist-info/RECORD
