Metadata-Version: 2.1
Name: global-kmeans-pp
Version: 0.1.0
Summary: A library for implementing the global k-means and the global k-means++ clustering algorithms.
Author-email: Georgios Vardakas <g.vardakas@uoi.gr>
Maintainer-email: Georgios Vardakas <g.vardakas@uoi.gr>
License: MIT License
Project-URL: Homepage, https://github.com/gvardakas/global-kmeans-pp
Project-URL: Issues, https://github.com/gvardakas/global-kmeans-pp/issues
Keywords: clustering,k-means,clustering error,global optimization,global k-means,k-means++,global k-means++
Classifier: Programming Language :: Python :: 3
Classifier: License :: OSI Approved :: MIT License
Classifier: Operating System :: OS Independent
Requires-Python: >=3.10
License-File: LICENSE
Requires-Dist: numpy
Requires-Dist: scikit-learn
